tuxbuild/__init__.py
tuxbuild/__main__.py
tuxbuild/cli.py
tuxbuild-0.12.0.dist-info/LICENSE
tuxbuild-0.12.0.dist-info/METADATA
tuxbuild-0.12.0.dist-info/WHEEL
tuxbuild-0.12.0.dist-info/entry_points.txt
tuxbuild-0.12.0.dist-info/top_level.txt
tuxbuild-0.12.0.dist-info/RECORD
